am91/gaia/__init__.py
am91/gaia/__main__.py
am91/gaia/cli.py
am91/gaia/config.py
am91/gaia/defs.py
am91/gaia/generator.py
am91/gaia/manifest.py
am91/gaia/template/base/__init__.py
am91/gaia/template/base/manifest.py
am91_gaia-0.0.3.dist-info/LICENSE
am91_gaia-0.0.3.dist-info/METADATA
am91_gaia-0.0.3.dist-info/WHEEL
am91_gaia-0.0.3.dist-info/entry_points.txt
am91_gaia-0.0.3.dist-info/top_level.txt
am91_gaia-0.0.3.dist-info/RECORD
