Metadata-Version: 2.1
Name: am91-gaia
Version: 0.0.3
Summary: Project generator
Home-page: https://github.com/AlejandroAM91/gaia
Author: Alejandro Alonso Mayo
Author-email: alejandroalonsomayo@gmail.com
License: UNKNOWN
Download-URL: https://github.com/AlejandroAM91/gaia/archive/v0.0.3.tar.gz
Platform: UNKNOWN
Classifier: Programming Language :: Python :: 3.7
Classifier: License :: OSI Approved :: MIT License
Requires-Dist: jinja2
